metacsv/__about__.py
metacsv/__init__.py
metacsv/_compat.py
metacsv/core/__init__.py
metacsv/core/containers.py
metacsv/core/exceptions.py
metacsv/core/internals.py
metacsv/io/__init__.py
metacsv/io/converters.py
metacsv/io/parsers.py
metacsv/io/to_csv.py
metacsv/io/to_pandas.py
metacsv/io/to_xarray.py
metacsv/io/yaml_tools.py
metacsv/scripts/__init__.py
metacsv/scripts/convert.py
metacsv/scripts/version.py
MetaCSV-0.1.1.dist-info/AUTHORS.rst
MetaCSV-0.1.1.dist-info/LICENSE
MetaCSV-0.1.1.dist-info/METADATA
MetaCSV-0.1.1.dist-info/WHEEL
MetaCSV-0.1.1.dist-info/top_level.txt
MetaCSV-0.1.1.dist-info/RECORD
