Metadata-Version: 2.1
Name: MetaCSV
Version: 0.1.1
Summary: Tools for documentation-aware data reading, writing, and analysis
Home-page: https://github.com/delgadom/metacsv
Author: Michael Delgado
Author-email: delgado.michaelt@gmail.com
License: MIT
Keywords: MetaCSV
Platform: UNKNOWN
Classifier: Development Status :: 2 - Pre-Alpha
Classifier: Intended Audience :: Developers
Classifier: License :: OSI Approved :: MIT License
Classifier: Natural Language :: English
Classifier: Programming Language :: Python :: 2
Classifier: Programming Language :: Python :: 2.7
Classifier: Programming Language :: Python :: 3
Classifier: Programming Language :: Python :: 3.5
Classifier: Programming Language :: Python :: 3.6
Requires-Dist: pandas (>=0.17)
Requires-Dist: numpy (>=1.10)
Requires-Dist: pyyaml (>=3.0)
Provides-Extra: xarray
Requires-Dist: xarray (>=0.7) ; extra == 'xarray'
Requires-Dist: netCDF4 ; extra == 'xarray'
